{
  "source": ["tokens/**/*.json"],
  "platforms": {
    "css": {
      "transforms": ["attribute/cti", "name/kebab", "color/css", "fontFamily/css"],
      "prefix": "wf",
      "buildPath": "src/renderer/styles/",
      "files": [
        {
          "destination": "tokens.css",
          "format": "css/variables",
          "options": {
            "outputReferences": true
          }
        }
      ]
    },
    "js": {
      "transformGroup": "js",
      "buildPath": "src/renderer/styles/",
      "files": [
        {
          "destination": "tokens.js",
          "format": "javascript/es6"
        }
      ]
    },
    "ts": {
      "transformGroup": "js",
      "buildPath": "src/renderer/styles/",
      "files": [
        {
          "destination": "tokens.d.ts",
          "format": "typescript/es6-declarations"
        }
      ]
    }
  }
}
